vallox_websocket_api/__init__.py
vallox_websocket_api/client.py
vallox_websocket_api/exceptions.py
vallox_websocket_api/messages.py
vallox_websocket_api/py.typed
vallox_websocket_api/vallox.py
vallox_websocket_api/data/2.0.16.json
vallox_websocket_api/data/2.0.22.json
vallox_websocket_api/data/__init__.py
vallox_websocket_api/data/constants.py
vallox_websocket_api/data/model.py
vallox_websocket_api-5.4.0.dist-info/LICENSE.txt
vallox_websocket_api-5.4.0.dist-info/METADATA
vallox_websocket_api-5.4.0.dist-info/WHEEL
vallox_websocket_api-5.4.0.dist-info/top_level.txt
vallox_websocket_api-5.4.0.dist-info/zip-safe
vallox_websocket_api-5.4.0.dist-info/RECORD
