Metadata-Version: 2.2
Name: vallox_websocket_api
Version: 5.4.0
Summary: Vallox WebSocket API
Home-page: https://github.com/yozik04/vallox_websocket_api
Author: Jevgeni Kiski
Author-email: yozik04@gmail.com
License: LGPL 3
Project-URL: Bug Tracker, https://github.com/yozik04/vallox_websocket_api/issues
Keywords: vallox api
Classifier: Development Status :: 5 - Production/Stable
Classifier: Intended Audience :: Developers
Classifier: License :: OSI Approved :: GNU Lesser General Public License v3 (LGPLv3)
Classifier: Operating System :: OS Independent
Classifier: Programming Language :: Python
Classifier: Programming Language :: Python :: 3 :: Only
Classifier: Programming Language :: Python :: 3.9
Classifier: Programming Language :: Python :: 3.10
Classifier: Programming Language :: Python :: 3.11
Classifier: Programming Language :: Python :: 3.12
Requires-Python: <4,>=3.9.0
License-File: LICENSE.txt
Requires-Dist: websockets>=9.1
Requires-Dist: construct<3.0.0,>=2.9.0
Requires-Dist: aiohttp<4.0.0,>=3.7.0
